horus_remote_api/__init__.py
horus_remote_api/client.py
horus_remote_api/connection.py
horus_remote_api/connection_socketio.py
horus_remote_api/types.py
horus_remote_api/utils.py
horus_remote_api-0.1.1.dist-info/LICENSE
horus_remote_api-0.1.1.dist-info/METADATA
horus_remote_api-0.1.1.dist-info/WHEEL
horus_remote_api-0.1.1.dist-info/top_level.txt
horus_remote_api-0.1.1.dist-info/RECORD
