Metadata-Version: 2.1
Name: horus-remote-api
Version: 0.1.1
Summary: Horus remote API for HORISON.
Author: Horus View and Explore B.V.
Author-email: info@horus.nu
License: MIT
Classifier: Intended Audience :: Developers
Classifier: Operating System :: OS Independent
Classifier: Programming Language :: Python :: 3.8
Classifier: Programming Language :: Python :: 3.9
Classifier: Programming Language :: Python :: 3.10
Requires-Python: >=3.8
License-File: LICENSE
Requires-Dist: python-socketio (==4)
Requires-Dist: python-engineio (==3.14.2)
Requires-Dist: requests
Requires-Dist: tornado
Requires-Dist: websocket-client (>=0.54.0)
